hftool/__init__.py
hftool/__main__.py
hftool/cli.py
hftool/core/__init__.py
hftool/core/batch.py
hftool/core/benchmark.py
hftool/core/completion.py
hftool/core/config.py
hftool/core/device.py
hftool/core/doctor.py
hftool/core/download.py
hftool/core/history.py
hftool/core/metadata.py
hftool/core/models.py
hftool/core/parameters.py
hftool/core/registry.py
hftool/io/__init__.py
hftool/io/file_picker.py
hftool/io/input_loader.py
hftool/io/interactive_input.py
hftool/io/interactive_mode.py
hftool/io/output_handler.py
hftool/tasks/__init__.py
hftool/tasks/base.py
hftool/tasks/image_to_image.py
hftool/tasks/speech_to_text.py
hftool/tasks/text_to_image.py
hftool/tasks/text_to_speech.py
hftool/tasks/text_to_video.py
hftool/tasks/transformers_generic.py
hftool/utils/__init__.py
hftool/utils/deps.py
hftool/utils/docker.py
hftool/utils/errors.py
hftool/utils/progress.py
hftool-0.7.1.dist-info/METADATA
hftool-0.7.1.dist-info/WHEEL
hftool-0.7.1.dist-info/entry_points.txt
hftool-0.7.1.dist-info/top_level.txt
hftool-0.7.1.dist-info/RECORD
