Metadata-Version: 2.4
Name: hftool
Version: 0.7.1
Summary: A CLI for Hugging Face models: text-to-image, text-to-video, TTS, ASR, and more.
Author-email: zashboy <info@zashboy.com>
License: MIT License
Project-URL: Homepage, https://github.com/zb-ss/hftool
Project-URL: Repository, https://github.com/zb-ss/hftool
Project-URL: Issues, https://github.com/zb-ss/hftool/issues
Classifier: Development Status :: 4 - Beta
Classifier: Intended Audience :: Developers
Classifier: Intended Audience :: Science/Research
Classifier: License :: OSI Approved :: MIT License
Classifier: Programming Language :: Python :: 3
Classifier: Programming Language :: Python :: 3.10
Classifier: Programming Language :: Python :: 3.11
Classifier: Programming Language :: Python :: 3.12
Classifier: Operating System :: OS Independent
Classifier: Topic :: Scientific/Engineering :: Artificial Intelligence
Classifier: Topic :: Software Development :: Libraries :: Python Modules
Classifier: Topic :: Utilities
Classifier: Environment :: Console
Classifier: Typing :: Typed
Requires-Python: >=3.10
Requires-Dist: transformers>=4.45.0
Requires-Dist: click>=8.0.0
Requires-Dist: huggingface_hub>=0.20.0
Requires-Dist: rich>=13.0.0
Requires-Dist: python-dotenv>=1.0.0
Provides-Extra: with-image
Requires-Dist: Pillow>=9.0.0; extra == "with-image"
Provides-Extra: with-audio
Requires-Dist: soundfile>=0.12.0; extra == "with-audio"
Provides-Extra: with-http
Requires-Dist: requests>=2.20.0; extra == "with-http"
Provides-Extra: with-t2i
Requires-Dist: diffusers>=0.36.0; extra == "with-t2i"
Requires-Dist: Pillow>=9.0.0; extra == "with-t2i"
Requires-Dist: accelerate>=0.26.0; extra == "with-t2i"
Requires-Dist: protobuf>=3.20.0; extra == "with-t2i"
Requires-Dist: sentencepiece>=0.1.99; extra == "with-t2i"
Provides-Extra: with-t2v
Requires-Dist: diffusers>=0.36.0; extra == "with-t2v"
Requires-Dist: Pillow>=9.0.0; extra == "with-t2v"
Requires-Dist: accelerate>=0.26.0; extra == "with-t2v"
Requires-Dist: ftfy>=6.0.0; extra == "with-t2v"
Provides-Extra: with-tts
Requires-Dist: transformers>=4.45.0; extra == "with-tts"
Requires-Dist: soundfile>=0.12.0; extra == "with-tts"
Provides-Extra: with-stt
Requires-Dist: transformers>=4.45.0; extra == "with-stt"
Requires-Dist: soundfile>=0.12.0; extra == "with-stt"
Provides-Extra: with-audio-advanced
Requires-Dist: soundfile>=0.12.0; extra == "with-audio-advanced"
Requires-Dist: librosa>=0.9.0; extra == "with-audio-advanced"
Requires-Dist: scipy; extra == "with-audio-advanced"
Provides-Extra: with-vision-advanced
Requires-Dist: Pillow>=9.0.0; extra == "with-vision-advanced"
Requires-Dist: opencv-python-headless>=4.5.0; extra == "with-vision-advanced"
Provides-Extra: with-quantization
Requires-Dist: bitsandbytes>=0.39.0; extra == "with-quantization"
Provides-Extra: with-config
Requires-Dist: tomli<3.0,>=2.0.1; python_version < "3.11" and extra == "with-config"
Provides-Extra: with-interactive
Requires-Dist: InquirerPy<1.0,>=0.3.4; extra == "with-interactive"
Provides-Extra: with-repl
Requires-Dist: prompt_toolkit<4.0,>=3.0.0; extra == "with-repl"
Provides-Extra: dev
Requires-Dist: pytest>=7.0.0; extra == "dev"
Requires-Dist: pytest-cov>=4.0.0; extra == "dev"
Provides-Extra: all
Requires-Dist: Pillow>=9.0.0; extra == "all"
Requires-Dist: soundfile>=0.12.0; extra == "all"
Requires-Dist: requests>=2.20.0; extra == "all"
Requires-Dist: diffusers>=0.36.0; extra == "all"
Requires-Dist: accelerate>=0.26.0; extra == "all"
Requires-Dist: ftfy>=6.0.0; extra == "all"
Requires-Dist: protobuf>=3.20.0; extra == "all"
Requires-Dist: sentencepiece>=0.1.99; extra == "all"
Requires-Dist: librosa>=0.9.0; extra == "all"
Requires-Dist: scipy; extra == "all"
Requires-Dist: opencv-python-headless>=4.5.0; extra == "all"
Requires-Dist: tomli<3.0,>=2.0.1; python_version < "3.11" and extra == "all"
Requires-Dist: InquirerPy<1.0,>=0.3.4; extra == "all"
Requires-Dist: prompt_toolkit<4.0,>=3.0.0; extra == "all"
